opensesame_extensions/language_server/__init__.py
opensesame_extensions/language_server/language_server/__init__.py
opensesame_extensions/language_server/language_server/language_server.py
opensesame_extensions/language_server/language_server/lsp_code_edit_widgets/__init__.py
opensesame_extensions/language_server/language_server/lsp_code_edit_widgets/_css_code_edit.py
opensesame_extensions/language_server/language_server/lsp_code_edit_widgets/_json_code_edit.py
opensesame_extensions/language_server/language_server/lsp_code_edit_widgets/_language_server_code_edit.py
opensesame_extensions/language_server/language_server/lsp_code_edit_widgets/_python_code_edit.py
opensesame_extensions/language_server/language_server/lsp_code_edit_widgets/_r_code_edit.py
opensesame_extensions/language_server/language_server/lsp_code_edit_widgets/_typescript_code_edit.py
opensesame_extensions/language_server/language_server/lsp_code_edit_widgets/_yaml_code_edit.py
opensesame_extensions/language_server/language_server/preferences.ui
opensesame_extension_language_server-0.2.4.dist-info/METADATA
opensesame_extension_language_server-0.2.4.dist-info/WHEEL
opensesame_extension_language_server-0.2.4.dist-info/RECORD
