Metadata-Version: 2.1
Name: opensesame-extension-language-server
Version: 0.2.4
Summary: Adds language-server support to OpenSesame and Rapunzel
Home-page: https://rapunzel.cogsci.nl/manual/language-server/
License: COPYING
Author: Sebastiaan Mathôt
Author-email: s.mathot@cogsci.nl
Requires-Python: >=3.7
Classifier: License :: Other/Proprietary License
Classifier: Programming Language :: Python :: 3
Classifier: Programming Language :: Python :: 3.7
Classifier: Programming Language :: Python :: 3.8
Classifier: Programming Language :: Python :: 3.9
Classifier: Programming Language :: Python :: 3.10
Classifier: Programming Language :: Python :: 3.11
Requires-Dist: opensesame-core (>=4.0.0a0)
Requires-Dist: pyqode.language-server (>=0.2.3)
Project-URL: Repository, https://github.com/open-cogsci/opensesame-extension-language_server
